sql_injection_detection/__init__.py
sql_injection_detection/dataclass.py
sql_injection_detection/exceptions.py
sql_injection_detection/main.py
sql_injection_detection/mapping.py
sql_injection_detection/models/model__random_forest.joblib
sql_injection_detection/models/model__xgboost.joblib
sql_injection_detection/tempCodeRunnerFile.py
sql_injection_detection/vector_mapping.py
sql_injection_detection-0.1.1.dist-info/METADATA
sql_injection_detection-0.1.1.dist-info/WHEEL
sql_injection_detection-0.1.1.dist-info/RECORD
